Workbook

Sheet Raw Data
A1: Apple Inc. - Financial Statement Data (2019 - 2023)
A2: Year | B2: Revenue | C2: Net Income | D2: Total Assets | E2: Total Equity | F2: Total Debt | G2: Current Assets | H2: Current Liabilities
A3: 2019 | B3: 260174 | C3: 55256 | D3: 338516 | E3: 90488 | F3: {=D3:D7 - E3:E7} -> 248028 | G3: 162819 | H3: 105718
A4: 2020 | B4: 274515 | C4: 57411 | D4: 323888 | E4: 65339 | F4: 258549 | G4: 143713 | H4: 105392
A5: 2021 | B5: 365817 | C5: 94680 | D5: 351002 | E5: 63090 | F5: 287912 | G5: 134836 | H5: 125481
A6: 2022 | B6: 394328 | C6: 99803 | D6: 352755 | E6: 50672 | F6: 302083 | G6: 135405 | H6: 153982
A7: 2023 | B7: 383285 | C7: 96995 | D7: 352583 | E7: 62146 | F7: 290437 | G7: 143566 | H7: 145308

Sheet Ratio Analysis
A1: Apple Inc. - Financial Ratio Analysis (2019 - 2023)
A2: Year | B2: Net Profit Margin | C2: ROE | D2: ROA | E2: Current Ratio | F2: Debt to equity
A3: 2019 | B3: ='Raw Data'!C3/'Raw Data'!B3 -> 0.21238095 | C3: ='Raw Data'!C3/'Raw Data'!E3 -> 0.61064451 | D3: ='Raw Data'!C3/'Raw Data'!D3 -> 0.1632301 | E3: ='Raw Data'!G3/'Raw Data'!H3 -> 1.5401256 | F3: ='Raw Data'!F3/'Raw Data'!E3 -> 2.7410043
A4: 2020 | B4: ='Raw Data'!C4/'Raw Data'!B4 -> 0.20913611 | C4: ='Raw Data'!C4/'Raw Data'!E4 -> 0.87866359 | D4: ='Raw Data'!C4/'Raw Data'!D4 -> 0.17725572 | E4: ='Raw Data'!G4/'Raw Data'!H4 -> 1.3636044 | F4: ='Raw Data'!F4/'Raw Data'!E4 -> 3.9570394
A5: 2021 | B5: ='Raw Data'!C5/'Raw Data'!B5 -> 0.25881793 | C5: ='Raw Data'!C5/'Raw Data'!E5 -> 1.5007133 | D5: ='Raw Data'!C5/'Raw Data'!D5 -> 0.26974205 | E5: ='Raw Data'!G5/'Raw Data'!H5 -> 1.0745531 | F5: ='Raw Data'!F5/'Raw Data'!E5 -> 4.5635124
A6: 2022 | B6: ='Raw Data'!C6/'Raw Data'!B6 -> 0.25309641 | C6: ='Raw Data'!C6/'Raw Data'!E6 -> 1.9695887 | D6: ='Raw Data'!C6/'Raw Data'!D6 -> 0.28292441 | E6: ='Raw Data'!G6/'Raw Data'!H6 -> 0.87935603 | F6: ='Raw Data'!F6/'Raw Data'!E6 -> 5.9615369
A7: 2023 | B7: ='Raw Data'!C7/'Raw Data'!B7 -> 0.25306234 | C7: ='Raw Data'!C7/'Raw Data'!E7 -> 1.5607601 | D7: ='Raw Data'!C7/'Raw Data'!D7 -> 0.27509835 | E7: ='Raw Data'!G7/'Raw Data'!H7 -> 0.98801167 | F7: ='Raw Data'!F7/'Raw Data'!E7 -> 4.6734625

Sheet Dashboard
A1: Apple Inc. - Financial Performace Dashboard (2019 - 2023)
